<annotation>
	<folder>finaldataset</folder>
	<filename>0069.jpg</filename>
	<path>/home/danilo/Área de Trabalho/finaldataset/0069.jpg</path>
	<source>
		<database>Unknown</database>
	</source>
	<size>
		<width>1366</width>
		<height>768</height>
		<depth>3</depth>
	</size>
	<segmented>0</segmented>
	<object>
		<name>car</name>
		<pose>Unspecified</pose>
		<truncated>0</truncated>
		<difficult>0</difficult>
		<bndbox>
			<xmin>212</xmin>
			<ymin>480</ymin>
			<xmax>399</xmax>
			<ymax>585</ymax>
		</bndbox>
	</object>
	<object>
		<name>car</name>
		<pose>Unspecified</pose>
		<truncated>0</truncated>
		<difficult>0</difficult>
		<bndbox>
			<xmin>625</xmin>
			<ymin>403</ymin>
			<xmax>729</xmax>
			<ymax>446</ymax>
		</bndbox>
	</object>
	<object>
		<name>car</name>
		<pose>Unspecified</pose>
		<truncated>0</truncated>
		<difficult>0</difficult>
		<bndbox>
			<xmin>813</xmin>
			<ymin>442</ymin>
			<xmax>907</xmax>
			<ymax>527</ymax>
		</bndbox>
	</object>
	<object>
		<name>car</name>
		<pose>Unspecified</pose>
		<truncated>0</truncated>
		<difficult>0</difficult>
		<bndbox>
			<xmin>910</xmin>
			<ymin>419</ymin>
			<xmax>997</xmax>
			<ymax>478</ymax>
		</bndbox>
	</object>
	<object>
		<name>car</name>
		<pose>Unspecified</pose>
		<truncated>0</truncated>
		<difficult>0</difficult>
		<bndbox>
			<xmin>994</xmin>
			<ymin>553</ymin>
			<xmax>1206</xmax>
			<ymax>679</ymax>
		</bndbox>
	</object>
	<object>
		<name>car</name>
		<pose>Unspecified</pose>
		<truncated>1</truncated>
		<difficult>0</difficult>
		<bndbox>
			<xmin>1266</xmin>
			<ymin>517</ymin>
			<xmax>1366</xmax>
			<ymax>583</ymax>
		</bndbox>
	</object>
	<object>
		<name>car</name>
		<pose>Unspecified</pose>
		<truncated>1</truncated>
		<difficult>0</difficult>
		<bndbox>
			<xmin>1283</xmin>
			<ymin>582</ymin>
			<xmax>1366</xmax>
			<ymax>714</ymax>
		</bndbox>
	</object>
</annotation>
